README.rst
setup.py
sppclient.egg-info/PKG-INFO
sppclient.egg-info/SOURCES.txt
sppclient.egg-info/dependency_links.txt
sppclient.egg-info/entry_points.txt
sppclient.egg-info/requires.txt
sppclient.egg-info/top_level.txt
spplib/__init__.py
spplib/cli/__init__.py
spplib/cli/sppcli.py
spplib/cli/util.py
spplib/cli/commands/__init__.py
spplib/cli/commands/cmd_job.py
spplib/cli/commands/cmd_logs.py
spplib/cli/commands/cmd_resource.py
spplib/cli/commands/cmd_sla.py
spplib/cli/commands/cmd_vm.py
spplib/sdk/__init__.py
spplib/sdk/client.py
spplib/sdk/system.py