Metadata-Version: 2.1
Name: sppclient
Version: 0.60
Summary: A client for SPP
Home-page: https://github.com/sppautomation/sppclient
Author: Ben Jones
Author-email: ben.jones@ibm.com
License: Apache License 2.0
Keywords: development
Platform: UNKNOWN
Classifier: Development Status :: 4 - Beta
Classifier: Intended Audience :: Developers
Classifier: Topic :: Software Development
Classifier: License :: OSI Approved :: Apache Software License
Classifier: Programming Language :: Python :: 3
Classifier: Programming Language :: Python :: 3.6
Provides-Extra: dev
Provides-Extra: test
